qualifire/__init__.py
qualifire/client.py
qualifire/consts.py
qualifire/tracer_init.py
qualifire/types.py
qualifire/utils.py
qualifire-0.15.0.dist-info/METADATA
qualifire-0.15.0.dist-info/WHEEL
qualifire-0.15.0.dist-info/licenses/LICENSE
qualifire-0.15.0.dist-info/RECORD
