Metadata-Version: 2.4
Name: qualifire
Version: 0.15.0
Summary: Qualifire Python SDK
Project-URL: Homepage, https://github.com/qualifire-dev/qualifire
Project-URL: Repository, https://github.com/qualifire-dev/qualifire
Author-email: qualifire-dev <dror@qualifire.ai>
License-Expression: MIT
License-File: LICENSE
Classifier: Development Status :: 3 - Alpha
Classifier: Intended Audience :: Developers
Classifier: License :: OSI Approved :: MIT License
Classifier: Operating System :: OS Independent
Classifier: Programming Language :: Python :: 3
Classifier: Programming Language :: Python :: 3.8
Classifier: Programming Language :: Python :: 3.9
Classifier: Programming Language :: Python :: 3.10
Classifier: Programming Language :: Python :: 3.11
Classifier: Topic :: Software Development :: Libraries :: Python Modules
Requires-Python: <4,>=3.8
Requires-Dist: pydantic>=2.10.6
Requires-Dist: traceloop-sdk==0.40.4; python_version >= '3.10'
Requires-Dist: types-requests>=2.32.0.20241016
